pywsitest/__init__.py
pywsitest/rest_request.py
pywsitest/utils.py
pywsitest/ws_message.py
pywsitest/ws_response.py
pywsitest/ws_test.py
pywsitest/ws_timeout_error.py
pywsitest-0.3.8.dist-info/LICENSE
pywsitest-0.3.8.dist-info/METADATA
pywsitest-0.3.8.dist-info/WHEEL
pywsitest-0.3.8.dist-info/top_level.txt
pywsitest-0.3.8.dist-info/RECORD
