Metadata-Version: 2.1
Name: pywsitest
Version: 0.3.8
Summary: PYthon WebSocket Integration TESTing framework
Home-page: https://github.com/gridsmartercities/pywsitest
Author: Grid Smarter Cities
Author-email: open-source@gridsmartercities.com
License: MIT
Keywords: websocket integration test testing
Platform: UNKNOWN
Classifier: Intended Audience :: Developers
Classifier: Development Status :: 3 - Alpha
Classifier: Programming Language :: Python :: 3
Classifier: License :: OSI Approved :: MIT License
Classifier: Operating System :: OS Independent
Classifier: Natural Language :: English
Requires-Python: >=3.7
License-File: LICENSE
